Metadata-Version: 2.1
Name: qcloud-requests-auth
Version: 0.0.1
Summary:  Tencent cloud signature version 3 (TC3-HMAC-SHA256) signing process for the python requests module. Forked from  DavidMuller/aws-requests-auth
Home-page: https://github.com/davendu/qcloud-requests-auth
Author: Daven DU
Author-email: davendu@tencent.com
License: UNKNOWN
Platform: UNKNOWN
Classifier: License :: OSI Approved :: BSD License
Classifier: Programming Language :: Python
Classifier: Programming Language :: Python :: 3
License-File: LICENSE
